trnsfr/requirements.txt
trnsfr/trnsfr.py
trnsfr-1.1.dist-info/METADATA
trnsfr-1.1.dist-info/WHEEL
trnsfr-1.1.dist-info/entry_points.txt
trnsfr-1.1.dist-info/top_level.txt
trnsfr-1.1.dist-info/RECORD
