Metadata-Version: 2.4
Name: trnsfr
Version: 1.1
Summary: A simple Python script to upload files on transfer.sh servers from CLI.
Author-email: tdebize@mail.com
License-Expression: LGPL-3.0-or-later
Project-URL: Homepage, https://github.com/maaaaz/trnsfr
Keywords: trnsfr,transfer,transfersh,transfer.sh,file,upload,download,encrypt,decrypt,cli
Classifier: Topic :: Security
Classifier: Programming Language :: Python :: 3
Requires-Python: >=3
Requires-Dist: requests
Requires-Dist: requests_toolbelt
Requires-Dist: tqdm
Requires-Dist: validators
